<annotation>
	<folder>Butterfly</folder>
	<filename>butterfly26.jpeg</filename>
	<path>C:\Users\admin\IT3100\Butterfly\butterfly26.jpeg</path>
	<source>
		<database>Unknown</database>
	</source>
	<size>
		<width>225</width>
		<height>225</height>
		<depth>3</depth>
	</size>
	<segmented>0</segmented>
	<object>
		<name>Butterfly</name>
		<pose>Unspecified</pose>
		<truncated>0</truncated>
		<difficult>0</difficult>
		<bndbox>
			<xmin>8</xmin>
			<ymin>68</ymin>
			<xmax>221</xmax>
			<ymax>183</ymax>
		</bndbox>
	</object>
</annotation>
